django_reorder/__init__.py
django_reorder/reorder.py
django_reorder-0.2.1.dist-info/DESCRIPTION.rst
django_reorder-0.2.1.dist-info/METADATA
django_reorder-0.2.1.dist-info/RECORD
django_reorder-0.2.1.dist-info/WHEEL
django_reorder-0.2.1.dist-info/metadata.json
django_reorder-0.2.1.dist-info/top_level.txt
