Metadata-Version: 2.0
Name: django-reorder
Version: 0.2.1
Summary: A project that helps sorting querysets in a specific order
Home-page: https://github.com/bmispelon/django-reorder
Author: Baptiste Mispelon
Author-email: bmispelon@gmail.com
License: MIT
Keywords: django-reorder
Platform: UNKNOWN
Classifier: Development Status :: 3 - Alpha
Classifier: Framework :: Django
Classifier: Framework :: Django :: 1.8
Classifier: Framework :: Django :: 1.9
Classifier: Intended Audience :: Developers
Classifier: License :: OSI Approved :: BSD License
Classifier: Natural Language :: English
Classifier: Programming Language :: Python :: 2
Classifier: Programming Language :: Python :: 2.7
Classifier: Programming Language :: Python :: 3
Classifier: Programming Language :: Python :: 3.2
Classifier: Programming Language :: Python :: 3.3
Classifier: Programming Language :: Python :: 3.4
Classifier: Programming Language :: Python :: 3.5
